LICENSE.txt
README.md
setup.cfg
setup.py
aws_cloud_unmap.egg-info/PKG-INFO
aws_cloud_unmap.egg-info/SOURCES.txt
aws_cloud_unmap.egg-info/dependency_links.txt
aws_cloud_unmap.egg-info/entry_points.txt
aws_cloud_unmap.egg-info/requires.txt
aws_cloud_unmap.egg-info/top_level.txt
cloudunmap/__init__.py
cloudunmap/aws.py
cloudunmap/cli.py
cloudunmap/unmap.py
tests/test_aws.py
tests/test_cli.py
tests/test_linter.py
tests/test_unmap.py