Metadata-Version: 2.1
Name: aws-cloud-unmap
Version: 2.0.0
Summary: Remove terminated EC2 instances from AWS CloudMap service
Home-page: https://github.com/spreaker/aws-cloud-unmap
Download-URL: https://github.com/spreaker/aws-cloud-unmap/archive/2.0.0.tar.gz
Author: Spreaker
Author-email: dev@spreaker.com
Keywords: aws,cloud map
Requires-Python:  >= 3.11
Provides-Extra: dev
License-File: LICENSE.txt
